mytable_lucien/__init__.py
mytable_lucien/mycsv.py
mytable_lucien/myedit.py
mytable_lucien/mytools.py
mytable_lucien/myview.py
mytable_lucien-6.0.0.dist-info/LICENSE
mytable_lucien-6.0.0.dist-info/METADATA
mytable_lucien-6.0.0.dist-info/WHEEL
mytable_lucien-6.0.0.dist-info/top_level.txt
mytable_lucien-6.0.0.dist-info/RECORD
