Metadata-Version: 2.1
Name: mytable-lucien
Version: 6.0.0
Summary: A simple package for processing data in the form of a table.
Home-page: https://github.com/lucienshawls/mytable-lucien
Author: Lucien
Author-email: myxlc55@outlook.com
License: UNKNOWN
Platform: UNKNOWN
Classifier: Programming Language :: Python :: 3
Classifier: License :: OSI Approved :: MIT License
Classifier: Operating System :: OS Independent
License-File: LICENSE
